{
  "title": "Diablo: The Kingdom of Shadow",
  "author": "Richard A. Knaak",
  "genre": "Dark fantasy, sword-and-sorcery adventure, supernatural horror, and licensed video-game tie-in fiction",
  "audience": "Mature readers of Diablo lore, dark fantasy, horror, and action-oriented fantasy",
  "source_edition": "Pocket Books English edition; copyright 2002; ISBN 0-7434-2313-5",
  "isbn": "0-7434-2313-5",
  "confidence": "high",
  "notes": "Identity and edition verified against the supplied copyright page and Google Books bibliographic data. The source contains 210 form-feed pages; narrative lines are restricted to 65–10500."
}
